LICENSE
MANIFEST.in
README.md
requirements.txt
setup.py
quantiphyse_dce/__init__.py
quantiphyse_dce/_version.py
quantiphyse_dce/dce.png
quantiphyse_dce/dce.svg
quantiphyse_dce/pk_model.cpp
quantiphyse_dce/pk_model.pyx
quantiphyse_dce/process.py
quantiphyse_dce/widgets.py
quantiphyse_dce.egg-info/PKG-INFO
quantiphyse_dce.egg-info/SOURCES.txt
quantiphyse_dce.egg-info/dependency_links.txt
quantiphyse_dce.egg-info/entry_points.txt
quantiphyse_dce.egg-info/requires.txt
quantiphyse_dce.egg-info/top_level.txt
src/Optimizer_class.cpp
src/Optimizer_class.h
src/ToftsOrton.cpp
src/ToftsOrton.h
src/ToftsOrtonOffset.cpp
src/ToftsOrtonOffset.h
src/ToftsWeinOffset.cpp
src/ToftsWeinOffset.h
src/ToftsWeinOffsetVp.cpp
src/ToftsWeinOffsetVp.h
src/pkrun2.cpp
src/pkrun2.h
src/python_test.py
src/lmlib/lmcurve.cpp
src/lmlib/lmcurve.h
src/lmlib/lmmin.cpp
src/lmlib/lmmin.h